<?xml version="1.0" encoding="UTF-8"?>
<bundle>
  <!-- For menu caption in Action Bar -->
  <UIActionBar>
    <tooltip>
      <OnlyofficeOpen>تحرير بواسطة OnlyOffice</OnlyofficeOpen>
    </tooltip>
  </UIActionBar>
  <!-- Used in Administration-Content-Explorer in Views settings a popup with actions list -->
  <UITabForm>
    <label>
      <onlyofficeOpen>تحرير بواسطة OnlyOffice</onlyofficeOpen>
    </label>
  </UITabForm>
  
  <!-- For new document form -->
  <UINewDocumentForm>    <label>
      <option>
        <MicrosoftOfficeDocument>ملف Microsoft Word</MicrosoftOfficeDocument>
        <MicrosoftOfficeSpreadsheet>ملف Microsoft Excel</MicrosoftOfficeSpreadsheet>
        <MicrosoftOfficePresentation>ملف عرض Microsoft PowerPoint</MicrosoftOfficePresentation>
        <MicrosoftOfficeNewSheet>ورقة</MicrosoftOfficeNewSheet>
      </option>
    </label>
  </UINewDocumentForm>  
  
  <!-- Messages -->
  <OnlyofficeEditor>
    <message>
      <ViewerNotFound>المحرر OnlyOffice غير موجود</ViewerNotFound>
    </message>
    <error>
      <EditorCannotBeCreated>لا يمكن إنشاء المحرر. الرجاء إعادة المحاولة.</EditorCannotBeCreated>
      <CannotReadDocument>لا يمكن قراءة الملف. الرجاء إعادة المحاولة.</CannotReadDocument>
      <CannotCreateEditor>لا يمكن إنشاء محرر. الرجاء إعادة المحاولة.</CannotCreateEditor>
      <CannotSendEditorConfiguration>لا يمكن إرسال اعدادات المحرر. الرجاء إعادة المحاولة.</CannotSendEditorConfiguration>
      <CannotInitEditorConfiguration>لا يمكن تهيئة إعدادات المحرر. الرجاء إعادة المحاولة.</CannotInitEditorConfiguration>
      <InitializationError>خطأ في تهيئة المحرر. الرجاء إعادة المحاولة.</InitializationError>
      <DocumentIdRequired>طلب خاطئ: معرف الملف مطلوب.</DocumentIdRequired>
    </error>
  </OnlyofficeEditor>
</bundle>
